llamapublisher/__init__.py
llamapublisher/client.py
llamapublisher-0.1.0.dist-info/licenses/LICENSE
llamapublisher-0.1.0.dist-info/METADATA
llamapublisher-0.1.0.dist-info/WHEEL
llamapublisher-0.1.0.dist-info/entry_points.txt
llamapublisher-0.1.0.dist-info/top_level.txt
llamapublisher-0.1.0.dist-info/RECORD
