Metadata-Version: 2.4
Name: llamapublisher
Version: 0.1.0
Summary: A powerful library for AI-powered search and data processing
Home-page: https://github.com/llamasearchai/llamapublisher
Author: LlamaSearch AI
Author-email: info@llamasearchai.com
Project-URL: Bug Tracker, https://github.com/llamasearchai/llamapublisher/issues
Project-URL: Documentation, https://llamasearchai.github.io/llamapublisher/
Project-URL: Source Code, https://github.com/llamasearchai/llamapublisher
Classifier: Programming Language :: Python :: 3
Classifier: Programming Language :: Python :: 3.8
Classifier: Programming Language :: Python :: 3.9
Classifier: Programming Language :: Python :: 3.10
Classifier: Programming Language :: Python :: 3.11
Classifier: License :: OSI Approved :: MIT License
Classifier: Operating System :: OS Independent
Classifier: Development Status :: 4 - Beta
Classifier: Intended Audience :: Developers
Classifier: Topic :: Software Development :: Libraries :: Python Modules
Classifier: Topic :: Scientific/Engineering :: Artificial Intelligence
Requires-Python: >=3.8
License-File: LICENSE
Requires-Dist: numpy>=1.20.0
Requires-Dist: pandas>=1.3.0
Requires-Dist: requests>=2.25.0
Requires-Dist: tqdm>=4.62.0
Provides-Extra: dev
Requires-Dist: pytest>=6.0.0; extra == "dev"
Requires-Dist: pytest-cov>=2.12.0; extra == "dev"
Requires-Dist: black>=21.5b2; extra == "dev"
Requires-Dist: isort>=5.9.0; extra == "dev"
Requires-Dist: flake8>=3.9.0; extra == "dev"
Requires-Dist: mypy>=0.900; extra == "dev"
Provides-Extra: mlx
Requires-Dist: mlx>=0.0.5; extra == "mlx"
Provides-Extra: all
Requires-Dist: mlx>=0.0.5; extra == "all"
Requires-Dist: matplotlib>=3.4.0; extra == "all"
Requires-Dist: seaborn>=0.11.0; extra == "all"
Requires-Dist: scikit-learn>=1.0.0; extra == "all"
Dynamic: author
Dynamic: author-email
Dynamic: classifier
Dynamic: description
Dynamic: description-content-type
Dynamic: home-page
Dynamic: license-file
Dynamic: project-url
Dynamic: provides-extra
Dynamic: requires-dist
Dynamic: requires-python
Dynamic: summary
